CHANGES.txt
README.txt
setup.cfg
setup.py
collective/__init__.py
collective.akismet.egg-info/PKG-INFO
collective.akismet.egg-info/SOURCES.txt
collective.akismet.egg-info/dependency_links.txt
collective.akismet.egg-info/entry_points.txt
collective.akismet.egg-info/namespace_packages.txt
collective.akismet.egg-info/not-zip-safe
collective.akismet.egg-info/paster_plugins.txt
collective.akismet.egg-info/requires.txt
collective.akismet.egg-info/top_level.txt
collective/akismet/__init__.py
collective/akismet/configure.zcml
collective/akismet/interfaces.py
collective/akismet/validator.py
collective/akismet/browser/__init__.py
collective/akismet/browser/configure.zcml
collective/akismet/browser/controlpanel.py
collective/akismet/browser/validator.py
collective/akismet/browser/verifykey.py
collective/akismet/profiles/default/actionicons.xml
collective/akismet/profiles/default/controlpanel.xml
collective/akismet/profiles/default/metadata.xml
collective/akismet/profiles/default/registry.xml
collective/akismet/tests/__init__.py
collective/akismet/tests/layer.py
collective/akismet/tests/test_controlpanel.py
collective/akismet/tests/test_validator.py
docs/INSTALL.txt
docs/LICENSE.GPL
docs/LICENSE.txt