Metadata-Version: 1.0
Name: collective.akismet
Version: 1.0b1
Summary: Akismet plugin for plone.app.discussion
Home-page: http://pypi.python.org/pypi/collective.akismet
Author: Timo Stollenwerk
Author-email: timo@zmag.de
License: GPL
Keywords: plone discussion plone.app.discussion spam akismet
Platform: UNKNOWN
Classifier: Framework :: Plone
Classifier: Programming Language :: Python
